mbox_to_sqlite/__init__.py
mbox_to_sqlite/__main__.py
mbox_to_sqlite/cli.py
mbox_to_sqlite-0.1a0.dist-info/LICENSE
mbox_to_sqlite-0.1a0.dist-info/METADATA
mbox_to_sqlite-0.1a0.dist-info/WHEEL
mbox_to_sqlite-0.1a0.dist-info/entry_points.txt
mbox_to_sqlite-0.1a0.dist-info/top_level.txt
mbox_to_sqlite-0.1a0.dist-info/RECORD
