Metadata-Version: 2.1
Name: mbox-to-sqlite
Version: 0.1a0
Summary: Load email from .mbox files into SQLite
Home-page: https://github.com/simonw/mbox-to-sqlite
Author: Simon Willison
License: Apache License, Version 2.0
Project-URL: Issues, https://github.com/simonw/mbox-to-sqlite/issues
Project-URL: CI, https://github.com/simonw/mbox-to-sqlite/actions
Project-URL: Changelog, https://github.com/simonw/mbox-to-sqlite/releases
Requires-Python: >=3.7
License-File: LICENSE
Requires-Dist: click
Requires-Dist: sqlite-utils
Provides-Extra: test
Requires-Dist: pytest ; extra == 'test'
